pycodebox/__init__.py
pycodebox/learn.py
pycodebox/plotting.py
pycodebox/stats.py
pycodebox/styling.py
pycodebox/utils.py
pycodebox-1.0.0.dist-info/licenses/LICENSE
tests/__init__.py
tests/test_learn.py
tests/test_plotting.py
tests/test_stats.py
tests/test_styling.py
tests/test_utils.py
pycodebox-1.0.0.dist-info/METADATA
pycodebox-1.0.0.dist-info/WHEEL
pycodebox-1.0.0.dist-info/top_level.txt
pycodebox-1.0.0.dist-info/RECORD
